ctip/__init__.py
ctip/__main__.py
ctip/commands.py
ctip/entrypoint.py
ctip/exceptions.py
ctip/gen.py
ctip/models.py
ctip/utils.py
ctip-0.1.1.dist-info/DESCRIPTION.rst
ctip-0.1.1.dist-info/METADATA
ctip-0.1.1.dist-info/RECORD
ctip-0.1.1.dist-info/WHEEL
ctip-0.1.1.dist-info/entry_points.txt
ctip-0.1.1.dist-info/metadata.json
ctip-0.1.1.dist-info/top_level.txt
