Metadata-Version: 2.0
Name: ctip
Version: 0.1.1
Summary: Extendible configuration testing in parallel.
Home-page: https://github.com/becketta/ctip.git
Author: Aaron Beckett
Author-email: aminor65ii@gmail.com
License: MIT
Requires-Dist: pyparsing
